pyatoms/__init__.py
pyatoms/mse/__init__.py
pyatoms/mse/adsorption.py
pyatoms/mse/analysis.py
pyatoms/mse/composition.py
pyatoms/mse/diffusion.py
pyatoms/mse/md.py
pyatoms/mse/ml.py
pyatoms/mse/structure.py
pyatoms/utils/__init__.py
pyatoms/utils/bash.py
pyatoms/utils/file.py
pyatoms/utils/index.py
pyatoms/utils/loglib.py
pyatoms/utils/mathlib.py
pyatoms/utils/plot.py
pyatoms/utils/server.py
pyatoms/utils/slurm.py
pyatoms/utils/stats.py
pyatoms/utils/timelib.py
pyatoms/vasp/__init__.py
pyatoms/vasp/errors.py
pyatoms/vasp/inputs.py
pyatoms/vasp/outputs.py
pyatoms/vasp/run.py
pyatoms-0.0.1.dist-info/LICENSE
pyatoms-0.0.1.dist-info/METADATA
pyatoms-0.0.1.dist-info/WHEEL
pyatoms-0.0.1.dist-info/top_level.txt
pyatoms-0.0.1.dist-info/RECORD
